fortls/__init__.py
fortls/__main__.py
fortls/_version.py
fortls/constants.py
fortls/debug.py
fortls/fortls.schema.json
fortls/ftypes.py
fortls/helper_functions.py
fortls/interface.py
fortls/json_templates.py
fortls/jsonrpc.py
fortls/langserver.py
fortls/regex_patterns.py
fortls/schema.py
fortls/version.py
fortls/parsers/__init__.py
fortls/parsers/internal/__init__.py
fortls/parsers/internal/associate.py
fortls/parsers/internal/ast.py
fortls/parsers/internal/base.py
fortls/parsers/internal/block.py
fortls/parsers/internal/diagnostics.py
fortls/parsers/internal/do.py
fortls/parsers/internal/enum.py
fortls/parsers/internal/function.py
fortls/parsers/internal/if_block.py
fortls/parsers/internal/imports.py
fortls/parsers/internal/include.py
fortls/parsers/internal/interface.py
fortls/parsers/internal/intrinsic.modules.json
fortls/parsers/internal/intrinsic.procedures.json
fortls/parsers/internal/intrinsic.procedures.markdown.json
fortls/parsers/internal/intrinsics.py
fortls/parsers/internal/keywords.json
fortls/parsers/internal/method.py
fortls/parsers/internal/module.py
fortls/parsers/internal/parser.py
fortls/parsers/internal/program.py
fortls/parsers/internal/scope.py
fortls/parsers/internal/select.py
fortls/parsers/internal/statements.json
fortls/parsers/internal/submodule.py
fortls/parsers/internal/subroutine.py
fortls/parsers/internal/type.py
fortls/parsers/internal/use.py
fortls/parsers/internal/utilities.py
fortls/parsers/internal/variable.py
fortls/parsers/internal/where.py
fortls-3.2.1.dist-info/LICENSE
fortls-3.2.1.dist-info/METADATA
fortls-3.2.1.dist-info/WHEEL
fortls-3.2.1.dist-info/entry_points.txt
fortls-3.2.1.dist-info/top_level.txt
fortls-3.2.1.dist-info/RECORD
