Metadata-Version: 2.2
Name: fortls
Version: 3.2.1
Summary: fortls - Fortran Language Server
Author-email: Giannis Nikiteas <giannis.nikiteas@gmail.com>
License: MIT
Project-URL: homepage, https://fortls.fortran-lang.org
Project-URL: Documentation, https://fortls.fortran-lang.org
Project-URL: Changes, https://github.com/fortran-lang/fortls/blob/master/CHANGELOG.md
Project-URL: Tracker, https://github.com/fortran-lang/fortls/issues
Project-URL: Source Code, https://github.com/fortran-lang/fortls
Keywords: fortran,language server,language server protocol,lsp,fortls
Classifier: Development Status :: 4 - Beta
Classifier: Intended Audience :: Developers
Classifier: Intended Audience :: Science/Research
Classifier: License :: OSI Approved :: MIT License
Classifier: Natural Language :: English
Classifier: Programming Language :: Python
Classifier: Programming Language :: Python :: 3
Classifier: Programming Language :: Python :: 3.7
Classifier: Programming Language :: Python :: 3.8
Classifier: Programming Language :: Python :: 3.9
Classifier: Programming Language :: Python :: 3.10
Classifier: Programming Language :: Python :: 3.11
Classifier: Programming Language :: Python :: 3.12
Classifier: Programming Language :: Fortran
Classifier: Operating System :: Microsoft :: Windows
Classifier: Operating System :: POSIX
Classifier: Operating System :: Unix
Classifier: Operating System :: MacOS
Requires-Python: >=3.7
License-File: LICENSE
Requires-Dist: json5
Requires-Dist: packaging
Requires-Dist: importlib-metadata; python_version < "3.8"
Requires-Dist: typing-extensions; python_version < "3.8"
Provides-Extra: dev
Requires-Dist: pytest>=7.2.0; extra == "dev"
Requires-Dist: pytest-cov>=4.0.0; extra == "dev"
Requires-Dist: pytest-xdist>=3.0.2; extra == "dev"
Requires-Dist: black; extra == "dev"
Requires-Dist: isort; extra == "dev"
Requires-Dist: pre-commit; extra == "dev"
Requires-Dist: pydantic; extra == "dev"
Provides-Extra: docs
Requires-Dist: sphinx>=4.0.0; extra == "docs"
Requires-Dist: sphinx-argparse; extra == "docs"
Requires-Dist: sphinx-autodoc-typehints; extra == "docs"
Requires-Dist: sphinx_design; extra == "docs"
Requires-Dist: sphinx-copybutton; extra == "docs"
Requires-Dist: furo; extra == "docs"
Requires-Dist: myst-parser; extra == "docs"
Requires-Dist: sphinx-sitemap; extra == "docs"
